cacheproxy/__init__.py
cacheproxy/cli.py
cacheproxy/server.py
cacheproxy-0.1.0.dist-info/entry_points.txt
cacheproxy-0.1.0.dist-info/LICENSE
cacheproxy-0.1.0.dist-info/WHEEL
cacheproxy-0.1.0.dist-info/METADATA
cacheproxy-0.1.0.dist-info/RECORD
