Metadata-Version: 2.1
Name: cacheproxy
Version: 0.1.0
Summary: Simple Python cache/caching proxy for Web development and something else
Home-page: https://github.com/nolze/cacheproxy
License: MIT
Author: nolze
Author-email: nolze@int3.net
Requires-Python: >=3.8,<4.0
Classifier: License :: OSI Approved :: MIT License
Classifier: Programming Language :: Python :: 3
Classifier: Programming Language :: Python :: 3.8
Classifier: Programming Language :: Python :: 3.9
Classifier: Programming Language :: Python :: 3.10
Classifier: Programming Language :: Python :: 3.11
Requires-Dist: aiofiles (>=22.1.0,<23.0.0)
Requires-Dist: aiohttp-client-cache (>=0.7.3,<0.8.0)
Requires-Dist: aiohttp[speedups] (>=3.8.3,<4.0.0)
Requires-Dist: aiosqlite (>=0.17.0,<0.18.0)
Project-URL: Repository, https://github.com/nolze/cacheproxy
